nonebot_plugin_puzzle/__init__.py
nonebot_plugin_puzzle/rank.py
nonebot_plugin_puzzle/render.py
nonebot_plugin_puzzle/theme/33.png
nonebot_plugin_puzzle/theme/44.png
nonebot_plugin_puzzle/theme/55.png
nonebot_plugin_puzzle-1.0.4.dist-info/METADATA
nonebot_plugin_puzzle-1.0.4.dist-info/WHEEL
nonebot_plugin_puzzle-1.0.4.dist-info/RECORD
